pypi_publish_with_poetry_dogfood/__init__.py
pypi_publish_with_poetry_dogfood-0.1.3.dist-info/WHEEL
pypi_publish_with_poetry_dogfood-0.1.3.dist-info/METADATA
pypi_publish_with_poetry_dogfood-0.1.3.dist-info/RECORD
